add_wrapper.cpython-38-x86_64-linux-gnu.so
adam_fdc/__init__.py
adam_fdc/add.py
adam_fdc/addlib/__init__.py
adam_fdc_newypei-0.0.4.4.dist-info/LICENSE
adam_fdc_newypei-0.0.4.4.dist-info/METADATA
adam_fdc_newypei-0.0.4.4.dist-info/WHEEL
adam_fdc_newypei-0.0.4.4.dist-info/top_level.txt
adam_fdc_newypei-0.0.4.4.dist-info/RECORD
