Metadata-Version: 2.1
Name: adam-fdc-newypei
Version: 0.0.4.4
Summary: A python package for FDC
Home-page: https://gitee.com/newypei/adam
Author: Yipei Niu
Author-email: newypei@gmail.com
License: UNKNOWN
Project-URL: Bug Tracker, https://gitee.com/newypei/adam/issues
Platform: UNKNOWN
Classifier: Programming Language :: Python :: 3
Classifier: License :: OSI Approved :: MIT License
Classifier: Operating System :: OS Independent
Requires-Python: >=3.6
